clointfusion/__init__.py
clointfusion/check_system.py
clointfusion/cli/__init__.py
clointfusion/cli/cf.py
clointfusion/cli/cf_py.py
clointfusion/cli/st.py
clointfusion/clointfusion.py
clointfusion/exception_handler.py
clointfusion/functions/__init__.py
clointfusion/functions/browser.py
clointfusion/functions/folder.py
clointfusion/functions/keyboard.py
clointfusion/functions/message.py
clointfusion/functions/mouse.py
clointfusion/functions/screen_srcaping.py
clointfusion/functions/string.py
clointfusion/functions/utility.py
clointfusion/functions/voice.py
clointfusion/functions/window.py
clointfusion/resources/__init__.py
clointfusion/resources/Cloint-ICON-CDT.ico
clointfusion/resources/Cloint-ICON.ico
clointfusion/resources/Cloint-LOGO.PNG
clointfusion/resources/CLOINTFUSION.png
clointfusion/resources/CLOINTFUSION_round.png
clointfusion/resources/Splash.PNG
clointfusion/verify.py
clointfusion-1.1.7.dist-info/entry_points.txt
clointfusion-1.1.7.dist-info/WHEEL
clointfusion-1.1.7.dist-info/METADATA
clointfusion-1.1.7.dist-info/RECORD
