Metadata-Version: 2.1
Name: clointfusion
Version: 1.1.7
Summary: Python based Automation (RPA) Platform
Home-page: https://github.com/ClointFusion/ClointFusion
License: BSD
Keywords: ClointFusion,RPA,Python,Automation,BOT,Software BOT,ROBOT,Dost
Author: Clointfusion
Author-email: clointfusion@cloint.com
Requires-Python: >=3.7.1,<4.0.0
Classifier: Development Status :: 5 - Production/Stable
Classifier: Environment :: Console
Classifier: Framework :: Robot Framework
Classifier: Intended Audience :: Developers
Classifier: License :: OSI Approved :: BSD License
Classifier: License :: Other/Proprietary License
Classifier: Natural Language :: English
Classifier: Operating System :: OS Independent
Classifier: Programming Language :: Python
Classifier: Programming Language :: Python :: 3
Classifier: Programming Language :: Python :: 3.10
Classifier: Programming Language :: Python :: 3.8
Classifier: Programming Language :: Python :: 3.9
Classifier: Topic :: Software Development :: Build Tools
Requires-Dist: PyAutoGUI (>=0.9.53,<0.10.0)
Requires-Dist: PySimpleGUI (>=4.55.1,<5.0.0)
Requires-Dist: SpeechRecognition (>=3.8.1,<4.0.0)
Requires-Dist: click (>=8.0.3,<9.0.0)
Requires-Dist: clipboard (>=0.0.4,<0.0.5)
Requires-Dist: colored (>=1.4.3,<2.0.0)
Requires-Dist: cryptocode (>=0.1,<0.2)
Requires-Dist: emoji (>=1.6.1,<2.0.0)
Requires-Dist: helium (>=3.0.8,<4.0.0)
Requires-Dist: matplotlib (>=3.5.1,<4.0.0)
Requires-Dist: openpyxl (>=3.0.9,<4.0.0)
Requires-Dist: pandas (>=1.3.5,<2.0.0)
Requires-Dist: pyfiglet (>=0.8.post1,<0.9)
Requires-Dist: pyinspect (>=0.1.0,<0.2.0)
Requires-Dist: pyttsx3 (>=2.90,<3.0)
Requires-Dist: requests (>=2.26.0,<3.0.0)
Requires-Dist: rich (>=10.16.1,<11.0.0)
Requires-Dist: speedtest-cli (>=2.1.3,<3.0.0)
Requires-Dist: webdriver-manager (>=3.5.2,<4.0.0)
Requires-Dist: win10toast-click (>=0.1.2,<0.2.0)
Requires-Dist: xls2xlsx (>=0.1.5,<0.2.0)
Requires-Dist: xlsx2html (>=0.4.0,<0.5.0)
Requires-Dist: xlwt (>=1.3.0,<2.0.0)
Project-URL: Bug Reports, https://github.com/ClointFusion/ClointFusion/issues
Project-URL: Documentation, https://clointfusion.readthedocs.io
Project-URL: Date ❤️ with ClointFusion, https://sites.google.com/view/clointfusion-hackathon/date-with-clointfusion
Project-URL: Hackathon Website, https://tinyurl.com/ClointFusion
Project-URL: Medium, https://medium.com/@clointfusion/bd152f4a1e0d?source=friends_link&sk=25b6051d75a8a4bb3e9a3e1a46516766
Project-URL: Repository, https://github.com/ClointFusion/ClointFusion
Project-URL: WhatsApp Community, https://chat.whatsapp.com/JKr7m0avmkIFwYgMarShZG
Project-URL: Windows EXE, https://github.com/ClointFusion/ClointFusion/releases/download/v1.0.0/ClointFusion_Community_Edition.exe
